[
  {
    "id": "3856175081",
    "message": "<p>Nice extension. Would be great if you could also add the 'Suspend' option.</p>",
    "createdAt": "2018-04-15T11:14:27Z",
    "author": "jasir",
    "thread": "6488467972",
    "posts": []
  },
  {
    "id": "3930300786",
    "message": "<p>Thank you very much for your work! Just add the options: suspend, hibernate, block and it will be perfect. Greetings from an Ubuntu Budgie in Latin America.</p>",
    "createdAt": "2018-06-04T18:10:43Z",
    "author": "Shalem Dior Juz",
    "thread": "6488467972",
    "posts": []
  }
]